itva_utils_test/__init__.py
itva_utils_test/cut.py
itva_utils_test/cut_poly.py
itva_utils_test/draw.py
itva_utils_test/draw_poly.py
itva_utils_test/pull.py
itva_utils_test01-0.0.1.dist-info/METADATA
itva_utils_test01-0.0.1.dist-info/WHEEL
itva_utils_test01-0.0.1.dist-info/top_level.txt
itva_utils_test01-0.0.1.dist-info/RECORD
