Metadata-Version: 2.1
Name: itva-utils-test01
Version: 0.0.1
Summary: test
Home-page: https://github.com
Author: author
Author-email: xxxxxxxx@163.com
License: UNKNOWN
Platform: UNKNOWN
Requires-Dist: opencv-python
Requires-Dist: numpy
